biomedisa/__init__.py
biomedisa/__main__.py
biomedisa/deeplearning.py
biomedisa/interpolation.py
biomedisa/mesh.py
biomedisa/features/DataGenerator.py
biomedisa/features/DataGeneratorCrop.py
biomedisa/features/PredictDataGenerator.py
biomedisa/features/PredictDataGeneratorCrop.py
biomedisa/features/__init__.py
biomedisa/features/active_contour.py
biomedisa/features/assd.py
biomedisa/features/biomedisa_helper.py
biomedisa/features/create_slices.py
biomedisa/features/crop_helper.py
biomedisa/features/curvop_numba.py
biomedisa/features/django_env.py
biomedisa/features/keras_helper.py
biomedisa/features/nc_reader.py
biomedisa/features/pid.py
biomedisa/features/process_image.py
biomedisa/features/pycuda_test.py
biomedisa/features/remove_outlier.py
biomedisa/features/split_volume.py
biomedisa/features/amira_to_np/__init__.py
biomedisa/features/amira_to_np/amira_data_stream.py
biomedisa/features/amira_to_np/amira_grammar.py
biomedisa/features/amira_to_np/amira_header.py
biomedisa/features/amira_to_np/amira_helper.py
biomedisa/features/random_walk/__init__.py
biomedisa/features/random_walk/gpu_kernels.py
biomedisa/features/random_walk/pycuda_large.py
biomedisa/features/random_walk/pycuda_large_allx.py
biomedisa/features/random_walk/pycuda_small.py
biomedisa/features/random_walk/pycuda_small_allx.py
biomedisa/features/random_walk/pyopencl_large.py
biomedisa/features/random_walk/pyopencl_small.py
biomedisa/features/random_walk/rw_large.py
biomedisa/features/random_walk/rw_small.py
biomedisa-2024.5.22.dist-info/LICENSE
biomedisa-2024.5.22.dist-info/METADATA
biomedisa-2024.5.22.dist-info/WHEEL
biomedisa-2024.5.22.dist-info/top_level.txt
biomedisa-2024.5.22.dist-info/RECORD
