Metadata-Version: 2.1
Name: biomedisa
Version: 2024.5.22
Summary: Segmentation of 3D volumetric image data
Author: Philipp Lösel
Author-email: philipp.loesel@anu.edu.au
Project-URL: Homepage, https://biomedisa.info
Project-URL: Issues, https://github.com/biomedisa/biomedisa/issues
Project-URL: GitHub, https://github.com/biomedisa/biomedisa
Classifier: Programming Language :: Python :: 3
Classifier: License :: OSI Approved :: European Union Public Licence 1.2 (EUPL 1.2)
Classifier: Operating System :: OS Independent
Requires-Python: >=3.8
License-File: LICENSE
